[
  {
    "id": 10000,
    "name": "Loreal Paris Le Shadow Stick Göz Farı 115 Twinkly Rose(5)",
    "brand": "",
    "category": "fondoten",
    "categoryLabel": "Fondoten",
    "price": 1070,
    "imageUrl": "https://api.gratis.retter.io/1oakekr4e/CALL/Image/getImage/10208072-C7jzqabwnr-01_1024x1024.jpg",
    "productUrl": "https://www.gratis.com/far/loreal-paris-le-shadow-stick-goz-fari-115-twinkly-rose-p-10208072",
    "rating": 0,
    "reviews": 0,
    "source": "gratis"
  },
  {
    "id": 10001,
    "name": "Astra 12 Saat Dayanıklı Extra Siyah Kalem Eyeliner(7)",
    "brand": "",
    "category": "fondoten",
    "categoryLabel": "Fondoten",
    "price": 500,
    "imageUrl": "https://api.gratis.retter.io/1oakekr4e/CALL/Image/get/QhKaehav1x_400x250.png",
    "productUrl": "https://www.gratis.com/eyeliner/astra-12-saat-dayanikli-extra-siyah-kalem-eyeliner-p-10209612",
    "rating": 0,
    "reviews": 0,
    "source": "gratis"
  },
  {
    "id": 10002,
    "name": "Loreal Paris Le Shadow Stick Göz Farı 120 Magnetic Mauve(8)",
    "brand": "",
    "category": "fondoten",
    "categoryLabel": "Fondoten",
    "price": 1070,
    "imageUrl": "https://api.gratis.retter.io/1oakekr4e/CALL/Image/getImage/10208073-hj51EN7w4M-01_1024x1024.jpg",
    "productUrl": "https://www.gratis.com/far/loreal-paris-le-shadow-stick-goz-fari-120-magnetic-mauve-p-10208073",
    "rating": 0,
    "reviews": 0,
    "source": "gratis"
  },
  {
    "id": 10003,
    "name": "3 Tür",
    "brand": "",
    "category": "fondoten",
    "categoryLabel": "Fondoten",
    "price": 459,
    "imageUrl": "https://api.gratis.retter.io/1oakekr4e/CALL/Image/get/QhKaehav1x_400x250.png",
    "productUrl": "https://www.gratis.com/maskara/astra-instalength-uzunluk-veren-maskara-p-10209600",
    "rating": 0,
    "reviews": 0,
    "source": "gratis"
  },
  {
    "id": 10004,
    "name": "3 Tür",
    "brand": "",
    "category": "fondoten",
    "categoryLabel": "Fondoten",
    "price": 459,
    "imageUrl": "https://api.gratis.retter.io/1oakekr4e/CALL/Image/get/QhKaehav1x_400x250.png",
    "productUrl": "https://www.gratis.com/maskara/astra-instacurls-kivrim-etkili-maskara-p-10209604",
    "rating": 0,
    "reviews": 0,
    "source": "gratis"
  },
  {
    "id": 10005,
    "name": "Stellary Panther Black Volume Mascara 01 Black - Hypnotic Volume & Defined Lashes(11)",
    "brand": "",
    "category": "fondoten",
    "categoryLabel": "Fondoten",
    "price": 660,
    "imageUrl": "https://api.gratis.retter.io/1oakekr4e/CALL/Image/get/QhKaehav1x_400x250.png",
    "productUrl": "https://www.gratis.com/maskara/stellary-panther-black-volume-mascara-01-black-hypnotic-volume-defined-lashes-p-10209395",
    "rating": 0,
    "reviews": 0,
    "source": "gratis"
  },
  {
    "id": 10006,
    "name": "+4Beaulis Spin It Stick Göz Farı 711 Moss Green(88)",
    "brand": "",
    "category": "fondoten",
    "categoryLabel": "Fondoten",
    "price": 279,
    "imageUrl": "https://api.gratis.retter.io/1oakekr4e/CALL/Image/get/QhKaehav1x_400x250.png",
    "productUrl": "https://www.gratis.com/far/beaulis-spin-it-stick-goz-fari-711-moss-green-p-10202391",
    "rating": 0,
    "reviews": 0,
    "source": "gratis"
  },
  {
    "id": 10007,
    "name": "wet n wild Color Icon 5’li Far Paleti Full Bloomin(67)",
    "brand": "",
    "category": "fondoten",
    "categoryLabel": "Fondoten",
    "price": 500,
    "imageUrl": "https://api.gratis.retter.io/1oakekr4e/CALL/Image/get/QhKaehav1x_400x250.png",
    "productUrl": "https://www.gratis.com/far/wet-n-wild-color-icon-5-li-far-paleti-full-bloomin-p-10202713",
    "rating": 0,
    "reviews": 0,
    "source": "gratis"
  },
  {
    "id": 10008,
    "name": "Mixup! Kaş Şekillendirici Wax 50 ml(224)",
    "brand": "",
    "category": "fondoten",
    "categoryLabel": "Fondoten",
    "price": 229,
    "imageUrl": "https://api.gratis.retter.io/1oakekr4e/CALL/Image/get/QWbEhDA9Pl_400x250.png",
    "productUrl": "https://www.gratis.com/kas-sabitleyici/mixup-kas-sekillendirici-wax-50-ml-p-10350980",
    "rating": 0,
    "reviews": 0,
    "source": "gratis"
  },
  {
    "id": 10009,
    "name": "Maybelline New York Lash Sensational Body Siyah Maskara(119)",
    "brand": "",
    "category": "fondoten",
    "categoryLabel": "Fondoten",
    "price": 1700,
    "imageUrl": "https://api.gratis.retter.io/1oakekr4e/CALL/Image/getImage/10215005-CVNbq8Geyr-01_1024x1024.jpg",
    "productUrl": "https://www.gratis.com/maskara/maybelline-new-york-lash-sensational-body-siyah-maskara-p-10215005",
    "rating": 0,
    "reviews": 0,
    "source": "gratis"
  },
  {
    "id": 10010,
    "name": "Loreal Paris Telescopic Extensionist Maskara(20)",
    "brand": "",
    "category": "fondoten",
    "categoryLabel": "Fondoten",
    "price": 1699,
    "imageUrl": "https://api.gratis.retter.io/1oakekr4e/CALL/Image/getImage/10215840-yd0oAHg7Gi-01_1024x1024.jpg",
    "productUrl": "https://www.gratis.com/maskara/loreal-paris-telescopic-extensionist-maskara-p-10215840",
    "rating": 0,
    "reviews": 0,
    "source": "gratis"
  },
  {
    "id": 10011,
    "name": "Etude My Lash Kaş Serumu(5)",
    "brand": "",
    "category": "fondoten",
    "categoryLabel": "Fondoten",
    "price": 699,
    "imageUrl": "https://api.gratis.retter.io/1oakekr4e/CALL/Image/get/QhKaehav1x_400x250.png",
    "productUrl": "https://www.gratis.com/kas-maskarasi/etude-my-lash-kas-serumu-p-10214274",
    "rating": 0,
    "reviews": 0,
    "source": "gratis"
  },
  {
    "id": 10012,
    "name": "Show by Pastel Show Your Peace Transparan Kaş ve Kirpik Maskarası(162)",
    "brand": "",
    "category": "fondoten",
    "categoryLabel": "Fondoten",
    "price": 589,
    "imageUrl": "https://api.gratis.retter.io/1oakekr4e/CALL/Image/getImage/10260969-KVPF7aLU39-01_1024x1024.jpg",
    "productUrl": "https://www.gratis.com/kas-sabitleyici/show-by-pastel-show-your-peace-transparan-kas-ve-kirpik-maskarasi-p-10260969",
    "rating": 0,
    "reviews": 0,
    "source": "gratis"
  },
  {
    "id": 10013,
    "name": "3 Tür",
    "brand": "",
    "category": "fondoten",
    "categoryLabel": "Fondoten",
    "price": 459,
    "imageUrl": "https://api.gratis.retter.io/1oakekr4e/CALL/Image/get/QhKaehav1x_400x250.png",
    "productUrl": "https://www.gratis.com/maskara/astra-instavolume-hacim-veren-maskara-p-10209602",
    "rating": 0,
    "reviews": 0,
    "source": "gratis"
  },
  {
    "id": 10014,
    "name": "Colorgram Tintin Dory Far Paleti 01 Glitter Dory(10)",
    "brand": "",
    "category": "fondoten",
    "categoryLabel": "Fondoten",
    "price": 1299,
    "imageUrl": "https://api.gratis.retter.io/1oakekr4e/CALL/Image/get/QhKaehav1x_400x250.png",
    "productUrl": "https://www.gratis.com/far/colorgram-tintin-dory-far-paleti-01-glitter-dory-p-10214398",
    "rating": 0,
    "reviews": 0,
    "source": "gratis"
  },
  {
    "id": 10015,
    "name": "Maybelline New York Super Lock Brow Glue Kaş Sabitleyici Maskara Medium Brown(9)",
    "brand": "",
    "category": "fondoten",
    "categoryLabel": "Fondoten",
    "price": 1300,
    "imageUrl": "https://api.gratis.retter.io/1oakekr4e/CALL/Image/getImage/10210191-Bw7wO0CKQX-01_1024x1024.jpg",
    "productUrl": "https://www.gratis.com/kas-maskarasi/maybelline-new-york-super-lock-brow-glue-kas-sabitleyici-maskara-medium-brown-p-10210191",
    "rating": 0,
    "reviews": 0,
    "source": "gratis"
  },
  {
    "id": 10016,
    "name": "wet n wild Color Icon 5’li Far Paleti Petalette/Forget Me Not(124)",
    "brand": "",
    "category": "fondoten",
    "categoryLabel": "Fondoten",
    "price": 500,
    "imageUrl": "https://api.gratis.retter.io/1oakekr4e/CALL/Image/get/QhKaehav1x_400x250.png",
    "productUrl": "https://www.gratis.com/far/wet-n-wild-color-icon-5-li-far-paleti-petalette-forget-me-not-p-10462177",
    "rating": 0,
    "reviews": 0,
    "source": "gratis"
  },
  {
    "id": 10017,
    "name": "wet n wild Color Icon 5’li Far Paleti Camo-Flaunt(60)",
    "brand": "",
    "category": "fondoten",
    "categoryLabel": "Fondoten",
    "price": 500,
    "imageUrl": "https://api.gratis.retter.io/1oakekr4e/CALL/Image/get/QhKaehav1x_400x250.png",
    "productUrl": "https://www.gratis.com/far/wet-n-wild-color-icon-5-li-far-paleti-camoflaunt-p-10462178",
    "rating": 0,
    "reviews": 0,
    "source": "gratis"
  },
  {
    "id": 10018,
    "name": "wet n wild Color Icon 5’li Far Paleti Walking On Eggshells(46)",
    "brand": "",
    "category": "fondoten",
    "categoryLabel": "Fondoten",
    "price": 500,
    "imageUrl": "https://api.gratis.retter.io/1oakekr4e/CALL/Image/get/QhKaehav1x_400x250.png",
    "productUrl": "https://www.gratis.com/far/wet-n-wild-color-icon-5-li-far-paleti-walking-on-eggshells-p-10462176",
    "rating": 0,
    "reviews": 0,
    "source": "gratis"
  },
  {
    "id": 10019,
    "name": "Beaulis Sharp It İnce Keçe Uçlu Eyeliner 100 Black(26)",
    "brand": "",
    "category": "fondoten",
    "categoryLabel": "Fondoten",
    "price": 239,
    "imageUrl": "https://api.gratis.retter.io/1oakekr4e/CALL/Image/get/QhKaehav1x_400x250.png",
    "productUrl": "https://www.gratis.com/eyeliner/beaulis-sharp-it-ince-kece-uclu-eyeliner-100-black-p-10207550",
    "rating": 0,
    "reviews": 0,
    "source": "gratis"
  },
  {
    "id": 10020,
    "name": "Loreal Paris Le Shadow Stick Göz Farı 105 Mesmerizing Gold(5)",
    "brand": "",
    "category": "fondoten",
    "categoryLabel": "Fondoten",
    "price": 1070,
    "imageUrl": "https://api.gratis.retter.io/1oakekr4e/CALL/Image/getImage/10208312-B4iy4OdjCu-01_1024x1024.jpg",
    "productUrl": "https://www.gratis.com/far/loreal-paris-le-shadow-stick-goz-fari-105-mesmerizing-gold-p-10208312",
    "rating": 0,
    "reviews": 0,
    "source": "gratis"
  },
  {
    "id": 10021,
    "name": "rom&nd Han All Fix Maskara L01 Long Black(95)",
    "brand": "",
    "category": "fondoten",
    "categoryLabel": "Fondoten",
    "price": 999,
    "imageUrl": "https://api.gratis.retter.io/1oakekr4e/CALL/Image/get/QhKaehav1x_400x250.png",
    "productUrl": "https://www.gratis.com/maskara/rom-nd-han-all-fix-maskara-l01-long-black-p-10204269",
    "rating": 0,
    "reviews": 0,
    "source": "gratis"
  },
  {
    "id": 10022,
    "name": "Maybelline New York Colossal Bubble Maskara(95)",
    "brand": "",
    "category": "fondoten",
    "categoryLabel": "Fondoten",
    "price": 1150,
    "imageUrl": "https://api.gratis.retter.io/1oakekr4e/CALL/Image/getImage/10208992-H1bWvYBwuL-01_1024x1024.jpg",
    "productUrl": "https://www.gratis.com/maskara/maybelline-new-york-colossal-bubble-maskara-p-10208992",
    "rating": 0,
    "reviews": 0,
    "source": "gratis"
  },
  {
    "id": 10023,
    "name": "Influence Beauty Mascara Manipula 01 Intense Black - Volumizing Mascara with Precision Brush(14)",
    "brand": "",
    "category": "fondoten",
    "categoryLabel": "Fondoten",
    "price": 859,
    "imageUrl": "https://api.gratis.retter.io/1oakekr4e/CALL/Image/get/QhKaehav1x_400x250.png",
    "productUrl": "https://www.gratis.com/maskara/influence-beauty-mascara-manipula-01-intense-black-volumizing-mascara-with-precision-brush-p-10209485",
    "rating": 0,
    "reviews": 0,
    "source": "gratis"
  },
  {
    "id": 10024,
    "name": "Flormar Mood Booster Yoğun Renk Veren Doğal Işıltılı Allık 002 Immortal Flower(18)",
    "brand": "",
    "category": "maskara",
    "categoryLabel": "Maskara",
    "price": 750,
    "imageUrl": "https://api.gratis.retter.io/1oakekr4e/CALL/Image/getImage/10208916-CQXdMlkUjN-01_1024x1024.jpg",
    "productUrl": "https://www.gratis.com/allik/flormar-mood-booster-yogun-renk-veren-dogal-isiltili-allik-002-immortal-flower-p-10208916",
    "rating": 0,
    "reviews": 0,
    "source": "gratis"
  },
  {
    "id": 10025,
    "name": "Stellary Perfect Matte Fixing Powder Pudra 02 Banana - Brightening Effect & Smooth Finish(3)",
    "brand": "",
    "category": "maskara",
    "categoryLabel": "Maskara",
    "price": 775,
    "imageUrl": "https://api.gratis.retter.io/1oakekr4e/CALL/Image/get/QhKaehav1x_400x250.png",
    "productUrl": "https://www.gratis.com/pudra/stellary-perfect-matte-fixing-powder-pudra-02-banana-brightening-effect-smooth-finish-p-10210413",
    "rating": 0,
    "reviews": 0,
    "source": "gratis"
  },
  {
    "id": 10026,
    "name": "Flormar Puffy Liquid Likit Kontür 001 Amber(59)",
    "brand": "",
    "category": "maskara",
    "categoryLabel": "Maskara",
    "price": 700,
    "imageUrl": "https://api.gratis.retter.io/1oakekr4e/CALL/Image/getImage/10209063-PggYue77Fj-01_1024x1024.jpg",
    "productUrl": "https://www.gratis.com/kontur/flormar-puffy-liquid-likit-kontur-001-amber-p-10209063",
    "rating": 0,
    "reviews": 0,
    "source": "gratis"
  },
  {
    "id": 10027,
    "name": "Golden Rose Make-up Fixing Spray 120 ml(62)",
    "brand": "",
    "category": "maskara",
    "categoryLabel": "Maskara",
    "price": 650,
    "imageUrl": "https://api.gratis.retter.io/1oakekr4e/CALL/Image/getImage/10288313-LAsxZEeRgh-01_1024x1024.jpg",
    "productUrl": "https://www.gratis.com/makyaj-sabitleyici/golden-rose-makeup-fixing-spray-120-ml-p-10288313",
    "rating": 0,
    "reviews": 0,
    "source": "gratis"
  },
  {
    "id": 10028,
    "name": "Beaulis Stop It Makyaj Sabitleyici Sprey(533)",
    "brand": "",
    "category": "maskara",
    "categoryLabel": "Maskara",
    "price": 209,
    "imageUrl": "https://api.gratis.retter.io/1oakekr4e/CALL/Image/get/QhKaehav1x_400x250.png",
    "productUrl": "https://www.gratis.com/makyaj-sabitleyici/beaulis-stop-it-makyaj-sabitleyici-sprey-p-10130879",
    "rating": 0,
    "reviews": 0,
    "source": "gratis"
  },
  {
    "id": 10029,
    "name": "Flormar Mood Booster Doğal Işıltılı Likit Aydınlatıcı 002 Sun Goddess(12)",
    "brand": "",
    "category": "maskara",
    "categoryLabel": "Maskara",
    "price": 750,
    "imageUrl": "https://api.gratis.retter.io/1oakekr4e/CALL/Image/getImage/10208672-kSOnLfmb0N-01_1024x1024.jpg",
    "productUrl": "https://www.gratis.com/aydinlatici/flormar-mood-booster-dogal-isiltili-likit-aydinlatici-002-sun-goddess-p-10208672",
    "rating": 0,
    "reviews": 0,
    "source": "gratis"
  },
  {
    "id": 10030,
    "name": "Flormar Mood Booster Yoğun Renk Veren Doğal Işıltılı Allık 004 Feel the Red(16)",
    "brand": "",
    "category": "maskara",
    "categoryLabel": "Maskara",
    "price": 750,
    "imageUrl": "https://api.gratis.retter.io/1oakekr4e/CALL/Image/getImage/10208673-Zjyexu2GZA-01_1024x1024.jpg",
    "productUrl": "https://www.gratis.com/allik/flormar-mood-booster-yogun-renk-veren-dogal-isiltili-allik-004-feel-the-red-p-10208673",
    "rating": 0,
    "reviews": 0,
    "source": "gratis"
  },
  {
    "id": 10031,
    "name": "Maybelline New York Instant Perfector Glow 4 Etki 1 Arada Fondöten 01 Light(25)",
    "brand": "",
    "category": "maskara",
    "categoryLabel": "Maskara",
    "price": 1800,
    "imageUrl": "https://api.gratis.retter.io/1oakekr4e/CALL/Image/getImage/10199074-UZkqfmM7af-01_1024x1024.jpg",
    "productUrl": "https://www.gratis.com/fondoten/maybelline-new-york-instant-perfector-glow-4-etki-1-arada-fondoten-01-light-p-10199074",
    "rating": 0,
    "reviews": 0,
    "source": "gratis"
  },
  {
    "id": 10032,
    "name": "Beaulis Finish It Transparan Sabitleyici Pudra 540 Rose Transparent(1005)",
    "brand": "",
    "category": "maskara",
    "categoryLabel": "Maskara",
    "price": 269,
    "imageUrl": "https://api.gratis.retter.io/1oakekr4e/CALL/Image/get/QhKaehav1x_400x250.png",
    "productUrl": "https://www.gratis.com/pudra/beaulis-finish-it-transparan-sabitleyici-pudra-540-rose-transparent-p-10213273",
    "rating": 0,
    "reviews": 0,
    "source": "gratis"
  },
  {
    "id": 10033,
    "name": "Astra Velvet Skin Loose Powder Toz Pudra Ghost(10)",
    "brand": "",
    "category": "maskara",
    "categoryLabel": "Maskara",
    "price": 720,
    "imageUrl": "https://api.gratis.retter.io/1oakekr4e/CALL/Image/get/QhKaehav1x_400x250.png",
    "productUrl": "https://www.gratis.com/pudra/astra-velvet-skin-loose-powder-toz-pudra-ghost-p-10209862",
    "rating": 0,
    "reviews": 0,
    "source": "gratis"
  },
  {
    "id": 10034,
    "name": "Beaulis Bloom It Krem Allık 569 Pink Whisper(16)",
    "brand": "",
    "category": "maskara",
    "categoryLabel": "Maskara",
    "price": 279,
    "imageUrl": "https://api.gratis.retter.io/1oakekr4e/CALL/Image/get/QhKaehav1x_400x250.png",
    "productUrl": "https://www.gratis.com/allik/beaulis-bloom-it-krem-allik-569-pink-whisper-p-10210618",
    "rating": 0,
    "reviews": 0,
    "source": "gratis"
  },
  {
    "id": 10035,
    "name": "Beaulis Fun Sugar and Spice Toz Allık 551 Shimmer Blush(72)",
    "brand": "",
    "category": "maskara",
    "categoryLabel": "Maskara",
    "price": 399,
    "imageUrl": "https://api.gratis.retter.io/1oakekr4e/CALL/Image/get/QhKaehav1x_400x250.png",
    "productUrl": "https://www.gratis.com/allik/beaulis-fun-sugar-and-spice-toz-allik-551-shimmer-blush-p-10203092",
    "rating": 0,
    "reviews": 0,
    "source": "gratis"
  },
  {
    "id": 10036,
    "name": "+1Maybelline New York Cloudtopia Köpük Dokulu Mat Allık 08 Enchanted Mauve(5)",
    "brand": "",
    "category": "maskara",
    "categoryLabel": "Maskara",
    "price": 1200,
    "imageUrl": "https://api.gratis.retter.io/1oakekr4e/CALL/Image/getImage/10215813-1IO1QEzS82-01_1024x1024.jpg",
    "productUrl": "https://www.gratis.com/allik/maybelline-new-york-cloudtopia-kopuk-dokulu-mat-allik-08-enchanted-mauve-p-10215813",
    "rating": 0,
    "reviews": 0,
    "source": "gratis"
  },
  {
    "id": 10037,
    "name": "Beaulis Fun Bake My Day Toz Pudra 108 Nude Transparent(13)",
    "brand": "",
    "category": "maskara",
    "categoryLabel": "Maskara",
    "price": 499,
    "imageUrl": "https://api.gratis.retter.io/1oakekr4e/CALL/Image/get/QhKaehav1x_400x250.png",
    "productUrl": "https://www.gratis.com/pudra/beaulis-fun-bake-my-day-toz-pudra-108-nude-transparent-p-10211251",
    "rating": 0,
    "reviews": 0,
    "source": "gratis"
  },
  {
    "id": 10038,
    "name": "Stellary Perfect Matte Fixing Powder Pudra 01 Transparent - Lightweight Setting & Oil Control(14)",
    "brand": "",
    "category": "maskara",
    "categoryLabel": "Maskara",
    "price": 775,
    "imageUrl": "https://api.gratis.retter.io/1oakekr4e/CALL/Image/get/QhKaehav1x_400x250.png",
    "productUrl": "https://www.gratis.com/pudra/stellary-perfect-matte-fixing-powder-pudra-01-transparent-lightweight-setting-oil-control-p-10210412",
    "rating": 0,
    "reviews": 0,
    "source": "gratis"
  },
  {
    "id": 10039,
    "name": "+1Maybelline New York Cloudtopia Köpük Dokulu Mat Allık 05 Coral Illusion(2)",
    "brand": "",
    "category": "maskara",
    "categoryLabel": "Maskara",
    "price": 1200,
    "imageUrl": "https://api.gratis.retter.io/1oakekr4e/CALL/Image/getImage/10215812-CDL1qgW5RG-01_1024x1024.jpg",
    "productUrl": "https://www.gratis.com/allik/maybelline-new-york-cloudtopia-kopuk-dokulu-mat-allik-05-coral-illusion-p-10215812",
    "rating": 0,
    "reviews": 0,
    "source": "gratis"
  },
  {
    "id": 10040,
    "name": "+1Maybelline New York Cloudtopia Köpük Dokulu Mat Allık 07 Moonlit Rose(7)",
    "brand": "",
    "category": "maskara",
    "categoryLabel": "Maskara",
    "price": 1200,
    "imageUrl": "https://api.gratis.retter.io/1oakekr4e/CALL/Image/get/mRyrBrZlps_400x250.png",
    "productUrl": "https://www.gratis.com/allik/maybelline-new-york-cloudtopia-kopuk-dokulu-mat-allik-07-moonlit-rose-p-10215814",
    "rating": 0,
    "reviews": 0,
    "source": "gratis"
  },
  {
    "id": 10041,
    "name": "+1Maybelline New York Cloudtopia Köpük Dokulu Mat Allık 04 Pink Daydream(4)",
    "brand": "",
    "category": "maskara",
    "categoryLabel": "Maskara",
    "price": 1200,
    "imageUrl": "https://api.gratis.retter.io/1oakekr4e/CALL/Image/getImage/10215811-dF9iuz9zuD-01_1024x1024.jpg",
    "productUrl": "https://www.gratis.com/allik/maybelline-new-york-cloudtopia-kopuk-dokulu-mat-allik-04-pink-daydream-p-10215811",
    "rating": 0,
    "reviews": 0,
    "source": "gratis"
  },
  {
    "id": 10042,
    "name": "Flormar Puffy Liquid Likit Kontür 003 Deep(33)",
    "brand": "",
    "category": "maskara",
    "categoryLabel": "Maskara",
    "price": 700,
    "imageUrl": "https://api.gratis.retter.io/1oakekr4e/CALL/Image/getImage/10209064-pRYZW01Cv0-01_1024x1024.jpg",
    "productUrl": "https://www.gratis.com/kontur/flormar-puffy-liquid-likit-kontur-003-deep-p-10209064",
    "rating": 0,
    "reviews": 0,
    "source": "gratis"
  },
  {
    "id": 10043,
    "name": "+1Maybelline New York Cloudtopia Köpük Dokulu Mat Allık 09 Dreamy Dawn(4)",
    "brand": "",
    "category": "maskara",
    "categoryLabel": "Maskara",
    "price": 1200,
    "imageUrl": "https://api.gratis.retter.io/1oakekr4e/CALL/Image/getImage/10215815-4vcXQKBflm-01_1024x1024.jpg",
    "productUrl": "https://www.gratis.com/allik/maybelline-new-york-cloudtopia-kopuk-dokulu-mat-allik-09-dreamy-dawn-p-10215815",
    "rating": 0,
    "reviews": 0,
    "source": "gratis"
  },
  {
    "id": 10044,
    "name": "Physicians Formula Butter Glow Likit Bronzer(1)",
    "brand": "",
    "category": "maskara",
    "categoryLabel": "Maskara",
    "price": 1290,
    "imageUrl": "https://api.gratis.retter.io/1oakekr4e/CALL/Image/get/QhKaehav1x_400x250.png",
    "productUrl": "https://www.gratis.com/bronzer/physicians-formula-butter-glow-likit-bronzer-p-10942763",
    "rating": 0,
    "reviews": 0,
    "source": "gratis"
  },
  {
    "id": 10045,
    "name": "Maybelline New York Instant Perfector Glow 4 Etki 1 Arada Fondöten 00 Fair Light(31)",
    "brand": "",
    "category": "maskara",
    "categoryLabel": "Maskara",
    "price": 1800,
    "imageUrl": "https://api.gratis.retter.io/1oakekr4e/CALL/Image/getImage/10199073-CAfBf4D7BM-01_1024x1024.jpg",
    "productUrl": "https://www.gratis.com/fondoten/maybelline-new-york-instant-perfector-glow-4-etki-1-arada-fondoten-00-fair-light-p-10199073",
    "rating": 0,
    "reviews": 0,
    "source": "gratis"
  },
  {
    "id": 10046,
    "name": "Flormar Mood Booster Doğal Işıltılı Likit Aydınlatıcı 001 Moon Glow(40)",
    "brand": "",
    "category": "maskara",
    "categoryLabel": "Maskara",
    "price": 750,
    "imageUrl": "https://api.gratis.retter.io/1oakekr4e/CALL/Image/getImage/10208671-HBbBSHvG0W-01_1024x1024.jpg",
    "productUrl": "https://www.gratis.com/aydinlatici/flormar-mood-booster-dogal-isiltili-likit-aydinlatici-001-moon-glow-p-10208671",
    "rating": 0,
    "reviews": 0,
    "source": "gratis"
  },
  {
    "id": 10047,
    "name": "+1Maybelline New York Cloudtopia Köpük Dokulu Mat Allık 03 Divine Crimson(3)",
    "brand": "",
    "category": "maskara",
    "categoryLabel": "Maskara",
    "price": 1200,
    "imageUrl": "https://api.gratis.retter.io/1oakekr4e/CALL/Image/getImage/10215810-j7pnSyXh5q-01_1024x1024.jpg",
    "productUrl": "https://www.gratis.com/allik/maybelline-new-york-cloudtopia-kopuk-dokulu-mat-allik-03-divine-crimson-p-10215810",
    "rating": 0,
    "reviews": 0,
    "source": "gratis"
  },
  {
    "id": 10048,
    "name": "+5Flormar Dewy Lip Glaze Dudak Parlatıcısı 004 Undressed(16)",
    "brand": "",
    "category": "ruj",
    "categoryLabel": "Ruj",
    "price": 850,
    "imageUrl": "https://api.gratis.retter.io/1oakekr4e/CALL/Image/get/mRyrBrZlps_400x250.png",
    "productUrl": "https://www.gratis.com/dudak-parlaticisi/flormar-dewy-lip-glaze-dudak-parlaticisi-004-undressed-p-10201091",
    "rating": 0,
    "reviews": 0,
    "source": "gratis"
  },
  {
    "id": 10049,
    "name": "+5Flormar Dewy Lip Glaze Dudak Parlatıcısı 016 Chery Blossom(25)",
    "brand": "",
    "category": "ruj",
    "categoryLabel": "Ruj",
    "price": 850,
    "imageUrl": "https://api.gratis.retter.io/1oakekr4e/CALL/Image/get/mRyrBrZlps_400x250.png",
    "productUrl": "https://www.gratis.com/dudak-parlaticisi/flormar-dewy-lip-glaze-dudak-parlaticisi-016-chery-blossom-p-10201092",
    "rating": 0,
    "reviews": 0,
    "source": "gratis"
  },
  {
    "id": 10050,
    "name": "+2Vivienne Sabo Jolies Levres Dudak Kalemi 102 Rose Nude - Precise Definition & Long-Lasting Wear(11)",
    "brand": "",
    "category": "ruj",
    "categoryLabel": "Ruj",
    "price": 340,
    "imageUrl": "https://api.gratis.retter.io/1oakekr4e/CALL/Image/get/QhKaehav1x_400x250.png",
    "productUrl": "https://www.gratis.com/dudak-kalemi/vivienne-sabo-jolies-levres-dudak-kalemi-102-rose-nude-precise-definition-longlasting-wear-p-10209310",
    "rating": 0,
    "reviews": 0,
    "source": "gratis"
  },
  {
    "id": 10051,
    "name": "LYKD Gleam Lip Fluid Dudak Parlatıcısı 296 Rose(34)",
    "brand": "",
    "category": "ruj",
    "categoryLabel": "Ruj",
    "price": 349,
    "imageUrl": "https://api.gratis.retter.io/1oakekr4e/CALL/Image/get/QhKaehav1x_400x250.png",
    "productUrl": "https://www.gratis.com/dudak-parlaticisi/lykd-gleam-lip-fluid-dudak-parlaticisi-296-rose-p-10202256",
    "rating": 0,
    "reviews": 0,
    "source": "gratis"
  },
  {
    "id": 10052,
    "name": "LYKD Gleam Lip Fluid Dudak Parlatıcısı 285 Peach(9)",
    "brand": "",
    "category": "ruj",
    "categoryLabel": "Ruj",
    "price": 349,
    "imageUrl": "https://api.gratis.retter.io/1oakekr4e/CALL/Image/get/QhKaehav1x_400x250.png",
    "productUrl": "https://www.gratis.com/dudak-parlaticisi/lykd-gleam-lip-fluid-dudak-parlaticisi-285-peach-p-10202255",
    "rating": 0,
    "reviews": 0,
    "source": "gratis"
  },
  {
    "id": 10053,
    "name": "LYKD Gleam Lip Fluid Dudak Parlatıcısı 585 Rosy Mauve(28)",
    "brand": "",
    "category": "ruj",
    "categoryLabel": "Ruj",
    "price": 349,
    "imageUrl": "https://api.gratis.retter.io/1oakekr4e/CALL/Image/get/QhKaehav1x_400x250.png",
    "productUrl": "https://www.gratis.com/dudak-parlaticisi/lykd-gleam-lip-fluid-dudak-parlaticisi-585-rosy-mauve-p-10202257",
    "rating": 0,
    "reviews": 0,
    "source": "gratis"
  },
  {
    "id": 10054,
    "name": "wet n wild Lip Oil Heart Rate(5)",
    "brand": "",
    "category": "ruj",
    "categoryLabel": "Ruj",
    "price": 519,
    "imageUrl": "https://api.gratis.retter.io/1oakekr4e/CALL/Image/get/QhKaehav1x_400x250.png",
    "productUrl": "https://www.gratis.com/dudak-parlaticisi/wet-n-wild-lip-oil-heart-rate-p-10205715",
    "rating": 0,
    "reviews": 0,
    "source": "gratis"
  },
  {
    "id": 10055,
    "name": "wet n wild Lip Oil Cocoa Rose(29)",
    "brand": "",
    "category": "ruj",
    "categoryLabel": "Ruj",
    "price": 569,
    "imageUrl": "https://api.gratis.retter.io/1oakekr4e/CALL/Image/get/QhKaehav1x_400x250.png",
    "productUrl": "https://www.gratis.com/dudak-parlaticisi/wet-n-wild-lip-oil-cocoa-rose-p-10205707",
    "rating": 0,
    "reviews": 0,
    "source": "gratis"
  },
  {
    "id": 10056,
    "name": "theBalm Lip Oil Dudak Yağı Too Slow, Mauve Over(12)",
    "brand": "",
    "category": "ruj",
    "categoryLabel": "Ruj",
    "price": 870,
    "imageUrl": "https://api.gratis.retter.io/1oakekr4e/CALL/Image/get/QhKaehav1x_400x250.png",
    "productUrl": "https://www.gratis.com/dudak-parlaticisi/thebalm-lip-oil-dudak-yagi-too-slow-mauve-over-p-10206207",
    "rating": 0,
    "reviews": 0,
    "source": "gratis"
  },
  {
    "id": 10057,
    "name": "theBalm Lip Oil Dudak Yağı Little Red Corvette(13)",
    "brand": "",
    "category": "ruj",
    "categoryLabel": "Ruj",
    "price": 870,
    "imageUrl": "https://api.gratis.retter.io/1oakekr4e/CALL/Image/get/QhKaehav1x_400x250.png",
    "productUrl": "https://www.gratis.com/dudak-parlaticisi/thebalm-lip-oil-dudak-yagi-little-red-corvette-p-10206205",
    "rating": 0,
    "reviews": 0,
    "source": "gratis"
  },
  {
    "id": 10058,
    "name": "theBalm Lip Oil Dudak Yağı Berry Fast(14)",
    "brand": "",
    "category": "ruj",
    "categoryLabel": "Ruj",
    "price": 870,
    "imageUrl": "https://api.gratis.retter.io/1oakekr4e/CALL/Image/get/QhKaehav1x_400x250.png",
    "productUrl": "https://www.gratis.com/dudak-parlaticisi/thebalm-lip-oil-dudak-yagi-berry-fast-p-10206204",
    "rating": 0,
    "reviews": 0,
    "source": "gratis"
  },
  {
    "id": 10059,
    "name": "theBalm Lip Oil Dudak Yağı Take The High Rose(10)",
    "brand": "",
    "category": "ruj",
    "categoryLabel": "Ruj",
    "price": 870,
    "imageUrl": "https://api.gratis.retter.io/1oakekr4e/CALL/Image/get/QhKaehav1x_400x250.png",
    "productUrl": "https://www.gratis.com/dudak-parlaticisi/thebalm-lip-oil-dudak-yagi-take-the-high-rose-p-10206208",
    "rating": 0,
    "reviews": 0,
    "source": "gratis"
  },
  {
    "id": 10060,
    "name": "+4rom&nd Glasting Color Gloss Dudak Parlatıcısı 04 Grapy Way(58)",
    "brand": "",
    "category": "ruj",
    "categoryLabel": "Ruj",
    "price": 999,
    "imageUrl": "https://api.gratis.retter.io/1oakekr4e/CALL/Image/get/QhKaehav1x_400x250.png",
    "productUrl": "https://www.gratis.com/dudak-parlaticisi/rom-nd-glasting-color-gloss-dudak-parlaticisi-04-grapy-way-p-10208388",
    "rating": 0,
    "reviews": 0,
    "source": "gratis"
  },
  {
    "id": 10061,
    "name": "wet n wild Lip Oil Merlot Glass(11)",
    "brand": "",
    "category": "ruj",
    "categoryLabel": "Ruj",
    "price": 549,
    "imageUrl": "https://api.gratis.retter.io/1oakekr4e/CALL/Image/get/QhKaehav1x_400x250.png",
    "productUrl": "https://www.gratis.com/dudak-parlaticisi/wet-n-wild-lip-oil-merlot-glass-p-10205717",
    "rating": 0,
    "reviews": 0,
    "source": "gratis"
  },
  {
    "id": 10062,
    "name": "wet n wild Lip Oil Vintage Society(7)",
    "brand": "",
    "category": "ruj",
    "categoryLabel": "Ruj",
    "price": 549,
    "imageUrl": "https://api.gratis.retter.io/1oakekr4e/CALL/Image/get/QhKaehav1x_400x250.png",
    "productUrl": "https://www.gratis.com/dudak-parlaticisi/wet-n-wild-lip-oil-vintage-society-p-10205711",
    "rating": 0,
    "reviews": 0,
    "source": "gratis"
  },
  {
    "id": 10063,
    "name": "Beaulis Drip It Dudak Yağı 197 Choco Touch(289)",
    "brand": "",
    "category": "ruj",
    "categoryLabel": "Ruj",
    "price": 239,
    "imageUrl": "https://api.gratis.retter.io/1oakekr4e/CALL/Image/get/QhKaehav1x_400x250.png",
    "productUrl": "https://www.gratis.com/dudak-parlaticisi/beaulis-drip-it-dudak-yagi-197-choco-touch-p-10207728",
    "rating": 0,
    "reviews": 0,
    "source": "gratis"
  },
  {
    "id": 10064,
    "name": "+1rom&nd Glasting Water Tint Renkli Dudak Parlatıcısı 17 Woody Sunset(151)",
    "brand": "",
    "category": "ruj",
    "categoryLabel": "Ruj",
    "price": 999,
    "imageUrl": "https://api.gratis.retter.io/1oakekr4e/CALL/Image/get/QhKaehav1x_400x250.png",
    "productUrl": "https://www.gratis.com/dudak-parlaticisi/rom-nd-glasting-water-tint-renkli-dudak-parlaticisi-17-woody-sunset-p-10204322",
    "rating": 0,
    "reviews": 0,
    "source": "gratis"
  },
  {
    "id": 10065,
    "name": "LYKD Gleam Lip Fluid Dudak Parlatıcısı 934 Pearl(3)",
    "brand": "",
    "category": "ruj",
    "categoryLabel": "Ruj",
    "price": 349,
    "imageUrl": "https://api.gratis.retter.io/1oakekr4e/CALL/Image/get/QhKaehav1x_400x250.png",
    "productUrl": "https://www.gratis.com/dudak-parlaticisi/lykd-gleam-lip-fluid-dudak-parlaticisi-934-pearl-p-10202254",
    "rating": 0,
    "reviews": 0,
    "source": "gratis"
  },
  {
    "id": 10066,
    "name": "Beauty Bomb Glossy Bossy Dudak Parlatıcısı 02 Rose Lemonade - High-Shine with Sweet Scent(1)",
    "brand": "",
    "category": "ruj",
    "categoryLabel": "Ruj",
    "price": 368,
    "imageUrl": "https://api.gratis.retter.io/1oakekr4e/CALL/Image/get/QhKaehav1x_400x250.png",
    "productUrl": "https://www.gratis.com/dudak-parlaticisi/beauty-bomb-glossy-bossy-dudak-parlaticisi-02-rose-lemonade-highshine-with-sweet-scent-p-10209180",
    "rating": 0,
    "reviews": 0,
    "source": "gratis"
  },
  {
    "id": 10067,
    "name": "Beauty Bomb Glossy Bossy Dudak Parlatıcısı 03 Double Date - High-Shine with Sweet Scent(1)",
    "brand": "",
    "category": "ruj",
    "categoryLabel": "Ruj",
    "price": 368,
    "imageUrl": "https://api.gratis.retter.io/1oakekr4e/CALL/Image/get/QhKaehav1x_400x250.png",
    "productUrl": "https://www.gratis.com/dudak-parlaticisi/beauty-bomb-glossy-bossy-dudak-parlaticisi-03-double-date-highshine-with-sweet-scent-p-10209181",
    "rating": 0,
    "reviews": 0,
    "source": "gratis"
  },
  {
    "id": 10068,
    "name": "Beauty Bomb Glossy Bossy Dudak Parlatıcısı 04 Hey Babe - High-Shine with Sweet Scent(7)",
    "brand": "",
    "category": "ruj",
    "categoryLabel": "Ruj",
    "price": 368,
    "imageUrl": "https://api.gratis.retter.io/1oakekr4e/CALL/Image/get/QhKaehav1x_400x250.png",
    "productUrl": "https://www.gratis.com/dudak-parlaticisi/beauty-bomb-glossy-bossy-dudak-parlaticisi-04-hey-babe-highshine-with-sweet-scent-p-10209182",
    "rating": 0,
    "reviews": 0,
    "source": "gratis"
  },
  {
    "id": 10069,
    "name": "+2Vivienne Sabo Tititint Lip Tint 02 Berry de Charme - Long-Lasting Color & Moisturizing Finish(24)",
    "brand": "",
    "category": "ruj",
    "categoryLabel": "Ruj",
    "price": 625,
    "imageUrl": "https://api.gratis.retter.io/1oakekr4e/CALL/Image/get/QhKaehav1x_400x250.png",
    "productUrl": "https://www.gratis.com/dudak-parlaticisi/vivienne-sabo-tititint-lip-tint-02-berry-de-charme-longlasting-color-moisturizing-finish-p-10209324",
    "rating": 0,
    "reviews": 0,
    "source": "gratis"
  },
  {
    "id": 10070,
    "name": "+2Vivienne Sabo Jolies Levres Dudak Kalemi 202 Cool Dark Rose - Precise Definition & Long-Lasting Wear(8)",
    "brand": "",
    "category": "ruj",
    "categoryLabel": "Ruj",
    "price": 340,
    "imageUrl": "https://api.gratis.retter.io/1oakekr4e/CALL/Image/get/QhKaehav1x_400x250.png",
    "productUrl": "https://www.gratis.com/dudak-kalemi/vivienne-sabo-jolies-levres-dudak-kalemi-202-cool-dark-rose-precise-definition-longlasting-wear-p-10209316",
    "rating": 0,
    "reviews": 0,
    "source": "gratis"
  },
  {
    "id": 10071,
    "name": "+2Vivienne Sabo Jolies Levres Dudak Kalemi 104 Light Brown - Precise Definition & Long-Lasting Wear(16)",
    "brand": "",
    "category": "ruj",
    "categoryLabel": "Ruj",
    "price": 340,
    "imageUrl": "https://api.gratis.retter.io/1oakekr4e/CALL/Image/get/QhKaehav1x_400x250.png",
    "productUrl": "https://www.gratis.com/dudak-kalemi/vivienne-sabo-jolies-levres-dudak-kalemi-104-light-brown-precise-definition-longlasting-wear-p-10209312",
    "rating": 0,
    "reviews": 0,
    "source": "gratis"
  }
]